zendesk_sdk/__init__.py
zendesk_sdk/client.py
zendesk_sdk/config.py
zendesk_sdk/exceptions.py
zendesk_sdk/http_client.py
zendesk_sdk/pagination.py
zendesk_sdk/clients/__init__.py
zendesk_sdk/clients/attachments.py
zendesk_sdk/clients/base.py
zendesk_sdk/clients/groups.py
zendesk_sdk/clients/organizations.py
zendesk_sdk/clients/search.py
zendesk_sdk/clients/ticket_fields.py
zendesk_sdk/clients/tickets.py
zendesk_sdk/clients/users.py
zendesk_sdk/clients/help_center/__init__.py
zendesk_sdk/clients/help_center/articles.py
zendesk_sdk/clients/help_center/categories.py
zendesk_sdk/clients/help_center/sections.py
zendesk_sdk/models/__init__.py
zendesk_sdk/models/base.py
zendesk_sdk/models/comment.py
zendesk_sdk/models/enriched_ticket.py
zendesk_sdk/models/group.py
zendesk_sdk/models/help_center.py
zendesk_sdk/models/organization.py
zendesk_sdk/models/search.py
zendesk_sdk/models/ticket.py
zendesk_sdk/models/user.py
python_zendesk_sdk-0.8.0.dist-info/METADATA
python_zendesk_sdk-0.8.0.dist-info/WHEEL
python_zendesk_sdk-0.8.0.dist-info/licenses/LICENSE
python_zendesk_sdk-0.8.0.dist-info/RECORD
